BinomialOptnCal/Binomial_Model.py
BinomialOptnCal/Main.py
BinomialOptnCal/UIDesign.py
BinomialOptnCal/__init__.py
BinomialOptnCal-0.1.0.dist-info/DESCRIPTION.rst
BinomialOptnCal-0.1.0.dist-info/METADATA
BinomialOptnCal-0.1.0.dist-info/RECORD
BinomialOptnCal-0.1.0.dist-info/WHEEL
BinomialOptnCal-0.1.0.dist-info/entry_points.txt
BinomialOptnCal-0.1.0.dist-info/metadata.json
BinomialOptnCal-0.1.0.dist-info/top_level.txt
